beekeeper/vector_stores/chroma/__init__.py
beekeeper/vector_stores/chroma/base.py
beekeeper_vector_stores_chroma-1.0.1.dist-info/METADATA
beekeeper_vector_stores_chroma-1.0.1.dist-info/WHEEL
beekeeper_vector_stores_chroma-1.0.1.dist-info/RECORD
