Metadata-Version: 2.4
Name: beekeeper-vector-stores-chroma
Version: 1.0.1
Summary: beekeeper vector_stores chroma extension
Author-email: Leonardo Furnielis <leonardofurnielis@outlook.com>
License: Apache-2.0
Requires-Python: <4.0,>=3.10
Requires-Dist: beekeeper-core<2.0.0,>=1.0.2
Requires-Dist: chromadb<1.1.0,>=1.0.13
Provides-Extra: dev
Requires-Dist: ruff>=0.11.13; extra == 'dev'
